{
  "$schema": "https://raw.githubusercontent.com/electron-userland/electron-builder/master/packages/app-builder-lib/scheme.json",
  "appId": "com.philibert.app",
  "productName": "Philibert",
  "directories": {
    "output": "out/make/nsis"
  },
  "executableName": "Philibert",
  "win": {
    "target": [
      {
        "target": "nsis",
        "arch": ["x64"]
      }
    ],
    "icon": "resources/icons/icon.ico"
  },
  "nsis": {
    "guid": "com.cline.gui",
    "oneClick": false,
    "allowToChangeInstallationDirectory": true,
    "createDesktopShortcut": true,
    "createStartMenuShortcut": true,
    "shortcutName": "Philibert",
    "artifactName": "${productName}-Setup-${version}.${ext}"
  }
}
